README.md
setup.cfg
setup.py
cloudmersive_dataintegration_api_client/__init__.py
cloudmersive_dataintegration_api_client/api_client.py
cloudmersive_dataintegration_api_client/configuration.py
cloudmersive_dataintegration_api_client/rest.py
cloudmersive_dataintegration_api_client.egg-info/PKG-INFO
cloudmersive_dataintegration_api_client.egg-info/SOURCES.txt
cloudmersive_dataintegration_api_client.egg-info/dependency_links.txt
cloudmersive_dataintegration_api_client.egg-info/requires.txt
cloudmersive_dataintegration_api_client.egg-info/top_level.txt
cloudmersive_dataintegration_api_client/api/__init__.py
cloudmersive_dataintegration_api_client/api/backup_convert_api.py
cloudmersive_dataintegration_api_client/models/__init__.py
cloudmersive_dataintegration_api_client/models/mssql_bak_enumerate_tables_result.py
cloudmersive_dataintegration_api_client/models/mssql_table.py
test/__init__.py
test/test_audio_api.py
test/test_backup_convert_api.py
test/test_media_information.py
test/test_mssql_bak_enumerate_tables_result.py
test/test_mssql_table.py
test/test_nsfw_result.py
test/test_nsfw_scanned_frame.py
test/test_split_video_result.py
test/test_still_frame.py
test/test_still_frames_result.py
test/test_video_api.py
test/test_video_file.py