Metadata-Version: 2.1
Name: cloudmersive-dataintegration-api-client
Version: 3.0.2
Summary: dataintegrationapi
Home-page: https://cloudmersive.com/data-integration-api
Author-email: 
License: UNKNOWN
Keywords: Swagger,dataintegrationapi
Platform: UNKNOWN
